precession/__init__.py
precession/__version__.py
precession/eccentricity.py
precession/precession.py
precession-2.1.1.dist-info/licenses/LICENSE
precession-2.1.1.dist-info/METADATA
precession-2.1.1.dist-info/WHEEL
precession-2.1.1.dist-info/top_level.txt
precession-2.1.1.dist-info/RECORD
