Metadata-Version: 2.4
Name: precession
Version: 2.1.1
Summary: Dynamics of precessing black-hole binaries
Home-page: https://github.com/dgerosa/precession
Author: Davide Gerosa
Author-email: davide.gerosa@unimib.it
License: MIT
Project-URL: Source Code, https://github.com/dgerosa/precession
Project-URL: Documentation, https://dgerosa.github.io/precession/
License-File: LICENSE
Requires-Dist: numpy
Requires-Dist: scipy>=1.8.0
Dynamic: author
Dynamic: author-email
Dynamic: description
Dynamic: description-content-type
Dynamic: home-page
Dynamic: license
Dynamic: license-file
Dynamic: project-url
Dynamic: requires-dist
Dynamic: summary
